setup.py
stoqplugin.py
nose_stoq.egg-info/PKG-INFO
nose_stoq.egg-info/SOURCES.txt
nose_stoq.egg-info/dependency_links.txt
nose_stoq.egg-info/entry_points.txt
nose_stoq.egg-info/requires.txt
nose_stoq.egg-info/top_level.txt
nose_stoq.egg-info/zip-safe