Metadata-Version: 1.0
Name: nose-stoq
Version: 0.1.3
Summary: A nose plugin for Stoq
Home-page: http://www.stoq.com.br/
Author: Johan Dahlin
Author-email: stoq-devel@async.com.br
License: MIT
Platform: UNKNOWN
